{
  "buildings": [
    {
      "id": "high-grass",
      "unitId": "B000:ZTtw",
      "name": "High Grass",
      "description": "",
      "hp": null,
      "armor": null,
      "craftableItems": []
    },
    {
      "id": "canopy-tree",
      "unitId": "B002:ZTtw",
      "name": "Canopy Tree",
      "description": "",
      "hp": null,
      "armor": null,
      "craftableItems": []
    },
    {
      "id": "normal-tree",
      "unitId": "B006:ZTtw",
      "name": "Normal Tree",
      "description": "",
      "hp": null,
      "armor": null,
      "craftableItems": []
    },
    {
      "id": "rotten-tree",
      "unitId": "B003:ZTtw",
      "name": "Rotten Tree",
      "description": "",
      "hp": null,
      "armor": null,
      "craftableItems": []
    },
    {
      "id": "magic-tree",
      "unitId": "B001:ZTtw",
      "name": "Magic Tree",
      "description": "",
      "hp": null,
      "armor": null,
      "craftableItems": []
    },
    {
      "id": "hanging-bridge",
      "unitId": "B005:YT42",
      "name": "hanging bridge",
      "description": "",
      "hp": null,
      "armor": null,
      "craftableItems": []
    },
    {
      "id": "entrance-left",
      "unitId": "B007:ZTtw",
      "name": "entrance_left",
      "description": "",
      "hp": null,
      "armor": null,
      "craftableItems": []
    },
    {
      "id": "new-bridge",
      "unitId": "B008:DTrf",
      "name": "new bridge",
      "description": "",
      "hp": null,
      "armor": null,
      "craftableItems": []
    },
    {
      "id": "entrance-right",
      "unitId": "B00C:ZTtw",
      "name": "entrance_right",
      "description": "",
      "hp": null,
      "armor": null,
      "craftableItems": []
    },
    {
      "id": "normal-tree-walkable",
      "unitId": "B009:ZTtw",
      "name": "Normal Tree(walkable)",
      "description": "",
      "hp": null,
      "armor": null,
      "craftableItems": []
    },
    {
      "id": "durotarpalm",
      "unitId": "B00B:ZTtw",
      "name": "durotarpalm",
      "description": "",
      "hp": null,
      "armor": null,
      "craftableItems": []
    },
    {
      "id": "canopy-durotarpalm",
      "unitId": "B00A:ZTtw",
      "name": "Canopy durotarpalm",
      "description": "",
      "hp": null,
      "armor": null,
      "craftableItems": []
    },
    {
      "id": "waterpalm",
      "unitId": "B00D:ZTtw",
      "name": "waterpalm",
      "description": "",
      "hp": null,
      "armor": null,
      "craftableItems": []
    },
    {
      "id": "durotartiltedpalm",
      "unitId": "B00E:ZTtw",
      "name": "durotartiltedpalm",
      "description": "",
      "hp": null,
      "armor": null,
      "craftableItems": []
    },
    {
      "id": "durotarpalm-walkable",
      "unitId": "B00F:ZTtw",
      "name": "durotarpalm(walkable)",
      "description": "",
      "hp": null,
      "armor": null,
      "craftableItems": []
    },
    {
      "id": "arena-gates1",
      "unitId": "B004:ZTw3",
      "name": "arena_gates1",
      "description": "",
      "hp": null,
      "armor": null,
      "craftableItems": []
    },
    {
      "id": "arena-gates2",
      "unitId": "B00G:ZTw3",
      "name": "arena_gates2",
      "description": "",
      "hp": null,
      "armor": null,
      "craftableItems": []
    },
    {
      "id": "magic-tree",
      "unitId": "DM02:ATtr",
      "name": "Magic Tree",
      "description": "",
      "hp": null,
      "armor": null,
      "craftableItems": []
    },
    {
      "id": "normal-tree",
      "unitId": "DM01:ZTtw",
      "name": "Normal Tree",
      "description": "",
      "hp": null,
      "armor": null,
      "craftableItems": []
    }
  ]
}
